RCAEval/__init__.py
rcaeval-1.2.0.dist-info/licenses/LICENSE
rcaeval-1.2.0.dist-info/METADATA
rcaeval-1.2.0.dist-info/WHEEL
rcaeval-1.2.0.dist-info/top_level.txt
rcaeval-1.2.0.dist-info/RECORD
