Metadata-Version: 2.4
Name: RCAEval
Version: 1.2.0
Summary: RCAEval: A Benchmark for Root Cause Analysis of Microservice Systems
License-File: LICENSE
Provides-Extra: default
Requires-Dist: aiobotocore==2.5.0; extra == "default"
Requires-Dist: aiohttp>=3.8.4; extra == "default"
Requires-Dist: aiohttp-retry==2.8.3; extra == "default"
Requires-Dist: aioitertools==0.11.0; extra == "default"
Requires-Dist: aiosignal==1.3.1; extra == "default"
Requires-Dist: amqp==5.1.1; extra == "default"
Requires-Dist: antlr4-python3-runtime==4.9.3; extra == "default"
Requires-Dist: appdirs==1.4.4; extra == "default"
Requires-Dist: asttokens==2.2.1; extra == "default"
Requires-Dist: async-timeout==4.0.2; extra == "default"
Requires-Dist: asyncssh==2.13.1; extra == "default"
Requires-Dist: atpublic==3.1.1; extra == "default"
Requires-Dist: attrs==23.1.0; extra == "default"
Requires-Dist: backcall==0.2.0; extra == "default"
Requires-Dist: billiard==3.6.4.0; extra == "default"
Requires-Dist: boto3==1.26.76; extra == "default"
Requires-Dist: botocore==1.29.76; extra == "default"
Requires-Dist: cairocffi==1.5.1; extra == "default"
Requires-Dist: CairoSVG==2.7.0; extra == "default"
Requires-Dist: causal-learn==0.1.3.3; extra == "default"
Requires-Dist: causality==0.0.10; extra == "default"
Requires-Dist: celery==5.2.7; extra == "default"
Requires-Dist: certifi==2023.5.7; extra == "default"
Requires-Dist: cffi==1.15.1; extra == "default"
Requires-Dist: cfgv==3.3.1; extra == "default"
Requires-Dist: charset-normalizer==3.1.0; extra == "default"
Requires-Dist: click==8.1.3; extra == "default"
Requires-Dist: click-didyoumean==0.3.0; extra == "default"
Requires-Dist: click-plugins==1.1.1; extra == "default"
Requires-Dist: click-repl==0.2.0; extra == "default"
Requires-Dist: colorama==0.4.6; extra == "default"
Requires-Dist: comm==0.1.3; extra == "default"
Requires-Dist: configobj==5.0.8; extra == "default"
Requires-Dist: contourpy==1.0.7; extra == "default"
Requires-Dist: cryptography==40.0.2; extra == "default"
Requires-Dist: cssselect2==0.7.0; extra == "default"
Requires-Dist: cycler==0.11.0; extra == "default"
Requires-Dist: debugpy==1.6.7; extra == "default"
Requires-Dist: decorator==5.1.1; extra == "default"
Requires-Dist: defusedxml==0.7.1; extra == "default"
Requires-Dist: dictdiffer==0.9.0; extra == "default"
Requires-Dist: diskcache==5.6.1; extra == "default"
Requires-Dist: distlib==0.3.6; extra == "default"
Requires-Dist: distro==1.8.0; extra == "default"
Requires-Dist: dpath==2.1.5; extra == "default"
Requires-Dist: dulwich==0.21.5; extra == "default"
Requires-Dist: et-xmlfile==1.1.0; extra == "default"
Requires-Dist: exceptiongroup==1.1.1; extra == "default"
Requires-Dist: executing==1.2.0; extra == "default"
Requires-Dist: filelock==3.12.0; extra == "default"
Requires-Dist: flatten-dict==0.4.2; extra == "default"
Requires-Dist: flufl.lock==7.1.1; extra == "default"
Requires-Dist: fonttools==4.39.4; extra == "default"
Requires-Dist: frozenlist>=1.3.3; extra == "default"
Requires-Dist: fsspec==2023.5.0; extra == "default"
Requires-Dist: funcy==2.0; extra == "default"
Requires-Dist: gitdb==4.0.10; extra == "default"
Requires-Dist: GitPython==3.1.31; extra == "default"
Requires-Dist: grandalf==0.8; extra == "default"
Requires-Dist: graphviz==0.20.1; extra == "default"
Requires-Dist: hydra-core==1.3.2; extra == "default"
Requires-Dist: identify==2.5.24; extra == "default"
Requires-Dist: idna==3.4; extra == "default"
Requires-Dist: igraph==0.10.4; extra == "default"
Requires-Dist: iniconfig==2.0.0; extra == "default"
Requires-Dist: ipykernel==6.23.1; extra == "default"
Requires-Dist: ipython==8.13.2; extra == "default"
Requires-Dist: iterative-telemetry==0.0.8; extra == "default"
Requires-Dist: jedi==0.18.2; extra == "default"
Requires-Dist: jmespath==1.0.1; extra == "default"
Requires-Dist: joblib==1.2.0; extra == "default"
Requires-Dist: jupyter_client==8.2.0; extra == "default"
Requires-Dist: jupyter_core==5.3.0; extra == "default"
Requires-Dist: kiwisolver==1.4.4; extra == "default"
Requires-Dist: kombu==5.2.4; extra == "default"
Requires-Dist: lazy_loader==0.2; extra == "default"
Requires-Dist: littleutils==0.2.2; extra == "default"
Requires-Dist: numpy<2; extra == "default"
Requires-Dist: llvmlite; extra == "default"
Requires-Dist: markdown-it-py==2.2.0; extra == "default"
Requires-Dist: mdurl==0.1.2; extra == "default"
Requires-Dist: multidict>=6.0.4; extra == "default"
Requires-Dist: nanotime==0.5.2; extra == "default"
Requires-Dist: nest-asyncio==1.5.6; extra == "default"
Requires-Dist: networkx==2.5; extra == "default"
Requires-Dist: nodeenv==1.8.0; extra == "default"
Requires-Dist: numba; extra == "default"
Requires-Dist: omegaconf==2.3.0; extra == "default"
Requires-Dist: openpyxl==3.1.2; extra == "default"
Requires-Dist: orjson==3.8.12; extra == "default"
Requires-Dist: outdated==0.2.2; extra == "default"
Requires-Dist: packaging==23.1; extra == "default"
Requires-Dist: pandas>2.0.1; extra == "default"
Requires-Dist: parso==0.8.3; extra == "default"
Requires-Dist: pathspec==0.11.1; extra == "default"
Requires-Dist: patsy==0.5.3; extra == "default"
Requires-Dist: pexpect==4.8.0; extra == "default"
Requires-Dist: pickleshare==0.7.5; extra == "default"
Requires-Dist: Pillow==9.5.0; extra == "default"
Requires-Dist: pingouin==0.5.3; extra == "default"
Requires-Dist: platformdirs==3.5.1; extra == "default"
Requires-Dist: pluggy==1.0.0; extra == "default"
Requires-Dist: pre-commit==3.3.2; extra == "default"
Requires-Dist: prompt-toolkit==3.0.38; extra == "default"
Requires-Dist: psutil==5.9.5; extra == "default"
Requires-Dist: ptyprocess==0.7.0; extra == "default"
Requires-Dist: pure-eval==0.2.2; extra == "default"
Requires-Dist: pyagrum; extra == "default"
Requires-Dist: pycparser==2.21; extra == "default"
Requires-Dist: pydot==1.4.2; extra == "default"
Requires-Dist: pydotplus==2.0.2; extra == "default"
Requires-Dist: Pygments==2.15.1; extra == "default"
Requires-Dist: pygtrie==2.5.0; extra == "default"
Requires-Dist: pyparsing==3.0.9; extra == "default"
Requires-Dist: pytest==7.3.1; extra == "default"
Requires-Dist: python-dateutil==2.8.2; extra == "default"
Requires-Dist: python-igraph==0.10.4; extra == "default"
Requires-Dist: pytz==2023.3; extra == "default"
Requires-Dist: PyYAML; extra == "default"
Requires-Dist: pyzmq>=25.0.2; extra == "default"
Requires-Dist: requests==2.30.0; extra == "default"
Requires-Dist: rich==13.3.5; extra == "default"
Requires-Dist: ruamel.yaml==0.17.26; extra == "default"
Requires-Dist: ruamel.yaml.clib>=0.2.7; extra == "default"
Requires-Dist: s3fs==2023.5.0; extra == "default"
Requires-Dist: s3transfer==0.6.1; extra == "default"
Requires-Dist: scikit-learn; extra == "default"
Requires-Dist: scikit-network>=0.31.0; extra == "default"
Requires-Dist: scipy>=1.10.1; extra == "default"
Requires-Dist: seaborn==0.12.2; extra == "default"
Requires-Dist: shortuuid==1.0.11; extra == "default"
Requires-Dist: shtab==1.6.1; extra == "default"
Requires-Dist: six==1.16.0; extra == "default"
Requires-Dist: smmap==5.0.0; extra == "default"
Requires-Dist: sqltrie==0.3.1; extra == "default"
Requires-Dist: stack-data==0.6.2; extra == "default"
Requires-Dist: statsmodels==0.14.0; extra == "default"
Requires-Dist: tabulate==0.9.0; extra == "default"
Requires-Dist: texttable==1.6.7; extra == "default"
Requires-Dist: threadpoolctl==3.1.0; extra == "default"
Requires-Dist: tigramite>=4.2.2.1; extra == "default"
Requires-Dist: tinycss2==1.2.1; extra == "default"
Requires-Dist: tk==0.1.0; extra == "default"
Requires-Dist: tomli==2.0.1; extra == "default"
Requires-Dist: tomlkit==0.11.8; extra == "default"
Requires-Dist: torch>=1.12.1; extra == "default"
Requires-Dist: tornado==6.3.2; extra == "default"
Requires-Dist: tqdm==4.65.0; extra == "default"
Requires-Dist: traitlets==5.9.0; extra == "default"
Requires-Dist: typing_extensions>=4.5.0; extra == "default"
Requires-Dist: tzdata==2023.3; extra == "default"
Requires-Dist: urllib3==1.26.15; extra == "default"
Requires-Dist: vine==5.0.0; extra == "default"
Requires-Dist: virtualenv==20.23.0; extra == "default"
Requires-Dist: voluptuous==0.13.1; extra == "default"
Requires-Dist: wcwidth==0.2.6; extra == "default"
Requires-Dist: webencodings==0.5.1; extra == "default"
Requires-Dist: wrapt==1.15.0; extra == "default"
Requires-Dist: xarray==2023.5.0; extra == "default"
Requires-Dist: yarl==1.9.2; extra == "default"
Requires-Dist: zc.lockfile==3.0.post1; extra == "default"
Requires-Dist: toml; extra == "default"
Provides-Extra: rcd
Requires-Dist: aiobotocore==2.5.0; extra == "rcd"
Requires-Dist: aiohttp==3.8.4; extra == "rcd"
Requires-Dist: aiohttp-retry==2.8.3; extra == "rcd"
Requires-Dist: aioitertools==0.11.0; extra == "rcd"
Requires-Dist: aiosignal==1.3.1; extra == "rcd"
Requires-Dist: amqp==5.1.1; extra == "rcd"
Requires-Dist: antlr4-python3-runtime==4.9.3; extra == "rcd"
Requires-Dist: appdirs==1.4.4; extra == "rcd"
Requires-Dist: asttokens==2.2.1; extra == "rcd"
Requires-Dist: async-timeout==4.0.2; extra == "rcd"
Requires-Dist: asyncssh==2.13.1; extra == "rcd"
Requires-Dist: atpublic==3.1.1; extra == "rcd"
Requires-Dist: attrs==23.1.0; extra == "rcd"
Requires-Dist: backcall==0.2.0; extra == "rcd"
Requires-Dist: billiard==3.6.4.0; extra == "rcd"
Requires-Dist: boto3==1.26.76; extra == "rcd"
Requires-Dist: botocore==1.29.76; extra == "rcd"
Requires-Dist: cairocffi==1.5.1; extra == "rcd"
Requires-Dist: CairoSVG==2.7.0; extra == "rcd"
Requires-Dist: causal-learn==0.1.2.3; extra == "rcd"
Requires-Dist: causality==0.0.10; extra == "rcd"
Requires-Dist: celery==5.2.7; extra == "rcd"
Requires-Dist: certifi==2023.5.7; extra == "rcd"
Requires-Dist: cffi==1.15.1; extra == "rcd"
Requires-Dist: cfgv==3.3.1; extra == "rcd"
Requires-Dist: charset-normalizer==3.1.0; extra == "rcd"
Requires-Dist: click==8.1.3; extra == "rcd"
Requires-Dist: click-didyoumean==0.3.0; extra == "rcd"
Requires-Dist: click-plugins==1.1.1; extra == "rcd"
Requires-Dist: click-repl==0.2.0; extra == "rcd"
Requires-Dist: colorama==0.4.6; extra == "rcd"
Requires-Dist: comm==0.1.3; extra == "rcd"
Requires-Dist: configobj==5.0.8; extra == "rcd"
Requires-Dist: contourpy==1.0.7; extra == "rcd"
Requires-Dist: cryptography==40.0.2; extra == "rcd"
Requires-Dist: cssselect2==0.7.0; extra == "rcd"
Requires-Dist: cycler==0.11.0; extra == "rcd"
Requires-Dist: debugpy==1.6.7; extra == "rcd"
Requires-Dist: decorator==5.1.1; extra == "rcd"
Requires-Dist: defusedxml==0.7.1; extra == "rcd"
Requires-Dist: dictdiffer==0.9.0; extra == "rcd"
Requires-Dist: diskcache==5.6.1; extra == "rcd"
Requires-Dist: distlib==0.3.6; extra == "rcd"
Requires-Dist: distro==1.8.0; extra == "rcd"
Requires-Dist: dpath==2.1.5; extra == "rcd"
Requires-Dist: dulwich==0.21.5; extra == "rcd"
Requires-Dist: dvc==2.57.3; extra == "rcd"
Requires-Dist: dvc-data==0.51.0; extra == "rcd"
Requires-Dist: dvc-http==2.30.2; extra == "rcd"
Requires-Dist: dvc-objects==0.22.0; extra == "rcd"
Requires-Dist: dvc-render==0.5.3; extra == "rcd"
Requires-Dist: dvc-s3==2.22.0; extra == "rcd"
Requires-Dist: dvc-studio-client==0.9.2; extra == "rcd"
Requires-Dist: dvc-task==0.2.1; extra == "rcd"
Requires-Dist: et-xmlfile==1.1.0; extra == "rcd"
Requires-Dist: exceptiongroup==1.1.1; extra == "rcd"
Requires-Dist: executing==1.2.0; extra == "rcd"
Requires-Dist: filelock==3.12.0; extra == "rcd"
Requires-Dist: flatten-dict==0.4.2; extra == "rcd"
Requires-Dist: flufl.lock==7.1.1; extra == "rcd"
Requires-Dist: fonttools==4.39.4; extra == "rcd"
Requires-Dist: frozenlist==1.3.3; extra == "rcd"
Requires-Dist: fsspec==2023.5.0; extra == "rcd"
Requires-Dist: funcy==2.0; extra == "rcd"
Requires-Dist: gitdb==4.0.10; extra == "rcd"
Requires-Dist: GitPython==3.1.31; extra == "rcd"
Requires-Dist: grandalf==0.8; extra == "rcd"
Requires-Dist: graphviz==0.20.1; extra == "rcd"
Requires-Dist: hydra-core==1.3.2; extra == "rcd"
Requires-Dist: identify==2.5.24; extra == "rcd"
Requires-Dist: idna==3.4; extra == "rcd"
Requires-Dist: igraph==0.10.4; extra == "rcd"
Requires-Dist: iniconfig==2.0.0; extra == "rcd"
Requires-Dist: ipykernel==6.23.1; extra == "rcd"
Requires-Dist: iterative-telemetry==0.0.8; extra == "rcd"
Requires-Dist: jedi==0.18.2; extra == "rcd"
Requires-Dist: jmespath==1.0.1; extra == "rcd"
Requires-Dist: joblib==1.2.0; extra == "rcd"
Requires-Dist: jupyter_client==8.2.0; extra == "rcd"
Requires-Dist: jupyter_core==5.3.0; extra == "rcd"
Requires-Dist: kiwisolver==1.4.4; extra == "rcd"
Requires-Dist: kombu==5.2.4; extra == "rcd"
Requires-Dist: lazy_loader==0.2; extra == "rcd"
Requires-Dist: littleutils==0.2.2; extra == "rcd"
Requires-Dist: llvmlite==0.39.1; extra == "rcd"
Requires-Dist: markdown-it-py==2.2.0; extra == "rcd"
Requires-Dist: mdurl==0.1.2; extra == "rcd"
Requires-Dist: multidict==6.0.4; extra == "rcd"
Requires-Dist: nanotime==0.5.2; extra == "rcd"
Requires-Dist: nest-asyncio==1.5.6; extra == "rcd"
Requires-Dist: networkx==2.5; extra == "rcd"
Requires-Dist: nodeenv==1.8.0; extra == "rcd"
Requires-Dist: numba==0.56.4; extra == "rcd"
Requires-Dist: numpy==1.23.5; extra == "rcd"
Requires-Dist: omegaconf==2.3.0; extra == "rcd"
Requires-Dist: openpyxl==3.1.2; extra == "rcd"
Requires-Dist: orjson==3.8.12; extra == "rcd"
Requires-Dist: outdated==0.2.2; extra == "rcd"
Requires-Dist: packaging==23.1; extra == "rcd"
Requires-Dist: pandas==2.0.1; extra == "rcd"
Requires-Dist: pandas-flavor==0.5.0; extra == "rcd"
Requires-Dist: parso==0.8.3; extra == "rcd"
Requires-Dist: pathspec==0.11.1; extra == "rcd"
Requires-Dist: patsy==0.5.3; extra == "rcd"
Requires-Dist: pexpect==4.8.0; extra == "rcd"
Requires-Dist: pickleshare==0.7.5; extra == "rcd"
Requires-Dist: Pillow==9.5.0; extra == "rcd"
Requires-Dist: pingouin==0.5.3; extra == "rcd"
Requires-Dist: platformdirs==3.5.1; extra == "rcd"
Requires-Dist: pluggy==1.0.0; extra == "rcd"
Requires-Dist: pre-commit==3.3.2; extra == "rcd"
Requires-Dist: prompt-toolkit==3.0.38; extra == "rcd"
Requires-Dist: psutil==5.9.5; extra == "rcd"
Requires-Dist: ptyprocess==0.7.0; extra == "rcd"
Requires-Dist: pure-eval==0.2.2; extra == "rcd"
Requires-Dist: pyagrum==1.8.0; extra == "rcd"
Requires-Dist: pycparser==2.21; extra == "rcd"
Requires-Dist: pydot==1.4.2; extra == "rcd"
Requires-Dist: pydotplus==2.0.2; extra == "rcd"
Requires-Dist: pygit2==1.12.1; extra == "rcd"
Requires-Dist: Pygments==2.15.1; extra == "rcd"
Requires-Dist: pygtrie==2.5.0; extra == "rcd"
Requires-Dist: pyparsing==3.0.9; extra == "rcd"
Requires-Dist: pytest==7.3.1; extra == "rcd"
Requires-Dist: python-dateutil==2.8.2; extra == "rcd"
Requires-Dist: python-igraph==0.10.4; extra == "rcd"
Requires-Dist: pytz==2023.3; extra == "rcd"
Requires-Dist: PyYAML==6.0; extra == "rcd"
Requires-Dist: pyzmq==25.0.2; extra == "rcd"
Requires-Dist: requests==2.30.0; extra == "rcd"
Requires-Dist: rich==13.3.5; extra == "rcd"
Requires-Dist: ruamel.yaml==0.17.26; extra == "rcd"
Requires-Dist: ruamel.yaml.clib==0.2.7; extra == "rcd"
Requires-Dist: s3fs==2023.5.0; extra == "rcd"
Requires-Dist: s3transfer==0.6.1; extra == "rcd"
Requires-Dist: scikit-learn==1.2.2; extra == "rcd"
Requires-Dist: scikit-network==0.31.0; extra == "rcd"
Requires-Dist: scipy==1.10.1; extra == "rcd"
Requires-Dist: scmrepo==1.0.3; extra == "rcd"
Requires-Dist: seaborn==0.12.2; extra == "rcd"
Requires-Dist: shortuuid==1.0.11; extra == "rcd"
Requires-Dist: shtab==1.6.1; extra == "rcd"
Requires-Dist: six==1.16.0; extra == "rcd"
Requires-Dist: smmap==5.0.0; extra == "rcd"
Requires-Dist: sqltrie==0.3.1; extra == "rcd"
Requires-Dist: stack-data==0.6.2; extra == "rcd"
Requires-Dist: statsmodels==0.14.0; extra == "rcd"
Requires-Dist: tabulate==0.9.0; extra == "rcd"
Requires-Dist: texttable==1.6.7; extra == "rcd"
Requires-Dist: threadpoolctl==3.1.0; extra == "rcd"
Requires-Dist: tigramite==4.2.2.1; extra == "rcd"
Requires-Dist: tinycss2==1.2.1; extra == "rcd"
Requires-Dist: tk==0.1.0; extra == "rcd"
Requires-Dist: tomli==2.0.1; extra == "rcd"
Requires-Dist: tomlkit==0.11.8; extra == "rcd"
Requires-Dist: torch==1.12.1; extra == "rcd"
Requires-Dist: tornado==6.3.2; extra == "rcd"
Requires-Dist: tqdm==4.65.0; extra == "rcd"
Requires-Dist: traitlets==5.9.0; extra == "rcd"
Requires-Dist: typing_extensions==4.5.0; extra == "rcd"
Requires-Dist: tzdata==2023.3; extra == "rcd"
Requires-Dist: urllib3==1.26.15; extra == "rcd"
Requires-Dist: vine==5.0.0; extra == "rcd"
Requires-Dist: virtualenv==20.23.0; extra == "rcd"
Requires-Dist: voluptuous==0.13.1; extra == "rcd"
Requires-Dist: wcwidth==0.2.6; extra == "rcd"
Requires-Dist: webencodings==0.5.1; extra == "rcd"
Requires-Dist: wrapt==1.15.0; extra == "rcd"
Requires-Dist: yarl==1.9.2; extra == "rcd"
Requires-Dist: zc.lockfile==3.0.post1; extra == "rcd"
Dynamic: description
Dynamic: description-content-type
Dynamic: license-file
Dynamic: provides-extra
Dynamic: summary
